README
setup.py
bookofnova/__init__.py
bookofnova/authentication.py
bookofnova/computelib.py
bookofnova/connections.py
bookofnova/info.py
bookofnova/logger.py
bookofnova/statuscodes.py
bookofnova.egg-info/PKG-INFO
bookofnova.egg-info/SOURCES.txt
bookofnova.egg-info/dependency_links.txt
bookofnova.egg-info/top_level.txt