Metadata-Version: 1.0
Name: bookofnova
Version: 0.007
Summary: Nova Compute Library for Python
Home-page: https://github.com/cloudnull/bookofnova, https://pypi.python.org/pypi/bookofnova
Author: Kevin Carter
Author-email: kevin.carter@rackspace.com
License: Apache2.0
Keywords: openstack,nova,compute,api,rackspace
Platform: UNKNOWN
Classifier: Intended Audience :: Information Technology
Classifier: Intended Audience :: System Administrators
Classifier: Intended Audience :: Developers
Classifier: Operating System :: OS Independent
Classifier: License :: OSI Approved :: Apache Software License
Classifier: Programming Language :: Python :: 2.6
Classifier: Programming Language :: Python :: 2.7
Classifier: Topic :: Utilities
Classifier: Topic :: Software Development :: Libraries :: Python Modules
